pytest_flakes.py
pytest_flakes-4.0.5.dist-info/LICENSE
pytest_flakes-4.0.5.dist-info/METADATA
pytest_flakes-4.0.5.dist-info/WHEEL
pytest_flakes-4.0.5.dist-info/entry_points.txt
pytest_flakes-4.0.5.dist-info/top_level.txt
pytest_flakes-4.0.5.dist-info/RECORD
