Metadata-Version: 2.1
Name: pytest-flakes
Version: 4.0.5
Summary: pytest plugin to check source code with pyflakes
Home-page: https://github.com/asmeurer/pytest-flakes
Author: Florian Schulze, Holger Krekel and Ronny Pfannschmidt
License: MIT license
Platform: UNKNOWN
Classifier: Development Status :: 5 - Production/Stable
Classifier: Framework :: Pytest
Classifier: Intended Audience :: Developers
Classifier: License :: OSI Approved :: MIT License
Classifier: Operating System :: OS Independent
Classifier: Programming Language :: Python :: 3
Classifier: Programming Language :: Python :: 3.5
Classifier: Programming Language :: Python :: 3.6
Classifier: Programming Language :: Python :: 3.7
Classifier: Programming Language :: Python :: 3.8
Classifier: Programming Language :: Python :: 3 :: Only
Classifier: Topic :: Software Development :: Testing
Requires-Python: >=3.5
License-File: LICENSE
